rstms_testmail/__init__.py
rstms_testmail/cli.py
rstms_testmail/counter.py
rstms_testmail/exception_handler.py
rstms_testmail/gmail.py
rstms_testmail/netstat.py
rstms_testmail/sendgrid_server.py
rstms_testmail/settings.py
rstms_testmail/shell.py
rstms_testmail/smtp_server.py
rstms_testmail/timer.py
rstms_testmail/version.py
rstms_testmail/watcher.py
rstms_testmail-0.2.10.dist-info/entry_points.txt
rstms_testmail-0.2.10.dist-info/licenses/LICENSE
rstms_testmail-0.2.10.dist-info/WHEEL
rstms_testmail-0.2.10.dist-info/METADATA
rstms_testmail-0.2.10.dist-info/RECORD
